example_pybr/__init__.py
example_pybr/example_pybr.py
example_pybr-0.1.dist-info/DESCRIPTION.rst
example_pybr-0.1.dist-info/METADATA
example_pybr-0.1.dist-info/RECORD
example_pybr-0.1.dist-info/WHEEL
example_pybr-0.1.dist-info/metadata.json
example_pybr-0.1.dist-info/top_level.txt
