Metadata-Version: 2.0
Name: example-pybr
Version: 0.1
Summary: Example of a simple Python package
Home-page: http://github.com/deboraazevedo/example_pybr
Author: Debora Azevedo
Author-email: deboraazevedo@gmail.com
License: MIT
Platform: UNKNOWN
